{
  "sw-bulk-edit": {
    "general": {
      "mainMenuTitle": "Bulk edit",
      "descriptionTextModule": "Module to bulk edit data",
      "defaultChangeLabel": "Change:"
    },
    "changeTypes": {
      "overwrite": "Overwrite",
      "clear": "Clear",
      "add": "Add",
      "remove": "Remove"
    },
    "product": {
      "textTitle": "Bulk edit: {productTotal} products",
      "messageEmptyTitle": "No products selected for bulk edit",
      "messageEmptySubline": "Please go back and select some products",
      "generalInformation": {
        "cardTitle": "General information",
        "description": {
          "changeLabel": "Change: Description"
        },
        "manufacturer": {
          "changeLabel": "Change: Manufacturer",
          "placeholderManufacturer": "Select manufacturer..."
        },
        "active": {
          "changeLabel": "Change: Active",
          "switchLabel": "Active"
        },
        "productPromotion": {
          "changeLabel": "Change: Product promotion",
          "switchLabel": "Product promotion"
        }
      },
      "prices": {
        "cardTitle": "Prices",
        "taxRate": {
          "changeLabel": "Change: Tax rate",
          "placeholderTax": "Select tax rate..."
        },
        "price": {
          "changeLabel": "Change: Price",
          "placeholderPrice": "Enter price..."
        },
        "purchasePrices": {
          "changeLabel": "Change: Purchase price",
          "placeholderPurchasePrices": "Enter purchase price..."
        },
        "listPrice": {
          "changeLabel": "Change: List price",
          "placeholderListPrice": "Enter list price..."
        }
      },
      "advancedPrices": {
        "cardTitle": "Advanced pricing",
        "changeLabel": "Change: Advanced pricing",
        "openModalButton": "Open advancing pricing"
      },
      "property": {
        "cardTitle": "Properties",
        "changeLabel": "Change: Properties"
      },
      "deliverability": {
        "cardTitle": "Deliverability",
        "stock": {
          "changeLabel": "Change: Stock",
          "placeholderStock": "Enter quantity in stock... "
        },
        "isCloseout": {
          "changeLabel": "Change: Clearance sale",
          "switchLabel": "Clearance sale"
        },
        "deliveryTime": {
          "changeLabel": "Change: Delivery time",
          "placeholderDeliveryTime": "Select delivery time..."
        },
        "restockTime": {
          "changeLabel": "Change: Restock time",
          "placeholderRestockTime": "Enter restock time in days..."
        },
        "freeShipping": {
          "changeLabel": "Change: Free shipping",
          "switchLabel": "Free shipping"
        },
        "minOrderQuantity": {
          "changeLabel": "Change: Min order quantity",
          "placeholderMinOrderQuantity": "Enter min order quantity..."
        },
        "purchaseSteps": {
          "changeLabel": "Change: Purchase steps",
          "placeholderPurchaseSteps": "Enter purchase step size..."
        },
        "maxOrderQuantity": {
          "changeLabel": "Change: Max order quantity",
          "placeholderMaxOrderQuantity": "Enter max order quantity..."
        }
      },
      "assignment": {
        "cardTitle": "Visibility & structure",
        "categories": {
          "changeLabel": "Change: Category",
          "placeholder": "Select categories..."
        },
        "tags": {
          "changeLabel": "Change: Tags",
          "placeholder": "Enter tags..."
        },
        "visibilities": {
          "changeLabel": "Change: Sales Channel",
          "placeholder": "Select Sales Channels..."
        },
        "searchKeywords": {
          "changeLabel": "Change: Search keywords",
          "placeholder": "Enter keywords..."
        }
      },
      "media": {
        "cardTitle": "Media",
        "changeLabel": "Change: Media"
      },
      "labelling": {
        "cardTitle": "Labelling",
        "releaseDate": {
          "changeLabel": "Change: Release date",
          "placeholderReleaseDate": "Enter release date..."
        }
      },
      "seo": {
        "cardTitle": "SEO",
        "metaTitle": {
          "changeLabel": "Change: Meta title",
          "placeholderMetaTitle": "Enter meta title..."
        },
        "metaDescription": {
          "changeLabel": "Change: Meta description",
          "placeholderMetaDescription": "Enter meta description..."
        },
        "seoKeywords": {
          "changeLabel": "Change: SEO keywords",
          "placeholderSeoKeywords": "Enter keywords..."
        }
      },
      "measuresAndPackaging": {
        "cardTitle": "Measures & packaging",
        "widthTitle": {
          "changeLabel": "Change: Width",
          "placeholder": "e.g. 500..."
        },
        "heightTitle": {
          "changeLabel": "Change: Height",
          "placeholder": "e.g. 200..."
        },
        "lengthTitle": {
          "changeLabel": "Change: Length",
          "placeholder": "e.g. 100..."
        },
        "weightTitle": {
          "changeLabel": "Change: Weight",
          "placeholder": "e.g. 0.4..."
        },
        "sellingUnitTitle": {
          "changeLabel": "Change: Selling unit",
          "placeholder": "Enter selling unit..."
        },
        "scaleUnitTitle": {
          "changeLabel": "Change: Scale unit",
          "placeholder": "Enter scale unit..."
        },
        "packUnitTitle": {
          "changeLabel": "Change: Packaging unit",
          "placeholder": "Enter packaging unit..."
        },
        "packUnitPluralTitle": {
          "changeLabel": "Change: Packaging unit plural",
          "placeholder": "Enter packaging unit plural..."
        },
        "basicUnitTitle": {
          "changeLabel": "Change: Basic unit",
          "placeholder": "Enter basic unit..."
        }
      },
      "featureSets": {
        "cardTitle": "Essential Characteristics",
        "changeLabel": "Change: Template",
        "placeholder": "Select a template..."
      },
      "customFields": {
        "cardTitle": "Custom fields",
        "changeLabel": "Change: {name}"
      }
    },
    "modal": {
      "confirm": {
        "title": "Bulk edit - Apply?",
        "description": "Apply changes to {itemCount} selected item? This action cannot be undone. | Apply changes to {itemCount} selected items? This action cannot be undone.",
        "switchLabel": "Trigger Flows with this bulk edit",
        "switchHelpText": "If this action is active, all triggers created in the Flow Builder are executed for all changes of this bulk edit. Under certain circumstances, this can lead to Flows being executed twice.",
        "alertTitle": "The following triggers/flows might be executed:",
        "triggeredFlows": {
          "orderDeliveries": {
            "key": "orderDeliveries",
            "label": "Delivery state changes"
          },
          "orderTransactions": {
            "key": "orderTransactions",
            "label": "Payment state changes"
          },
          "orders": {
            "key": "orders",
            "label": "Order state changes"
          }
        },
        "buttons": {
          "applyChanges": "Apply changes"
        }
      },
      "process": {
        "title": "Bulk edit - In process",
        "description": "Depending on the amount of changes, this may take a while.",
        "helpText": "Please be aware that manual changes to one of the selected items during the bulk edit process may yield unwanted results.",
        "buttons": {
          "cancel": "Cancel"
        }
      },
      "success": {
        "title": "Bulk edit - Success",
        "description": "Bulk edit finished."
      },
      "error": {
        "title": "Bulk edit - Error",
        "description": "Bulk edit finished with errors.",
        "buttons": {
          "openLog": "Open log file"
        }
      },
      "warningText": "Please wait for the bulk edit to complete. This may take a while. If you close the browser tab or cancel the process prematurely, not all changes will be applied. You can run the bulk edit again at any time."
    },
    "order": {
      "textTitle": "Bulk edit: {orderTotal} orders",
      "messageEmptyTitle": "No orders selected",
      "messageEmptySubline": "Go back and select orders.",
      "status": {
        "cardTitle": "Status",
        "payment": {
          "label": "Change: Payment status",
          "placeholder": "Select payment status..."
        },
        "shipping": {
          "label": "Change: Shipping status",
          "placeholder": "Select shipping status..."
        },
        "order": {
          "label": "Change: Order status",
          "placeholder": "Select order status..."
        },
        "statusMails": {
          "label": "Send: Status emails",
          "helpText": "Available only if status has been changed."
        },
        "documents": {
          "label": "Send: Documents",
          "helpText": "Available only if \"Send: Status emails\" is checked.",
          "options": {
            "newest": "Newest",
            "all": "All"
          },
          "documentType": {
            "invoices": "Invoices",
            "deliveryNotes": "Delivery notes",
            "creditNotes": "Credit notes",
            "cancellationInvoices": "Cancellation notes"
          },
          "skipSentDocuments": "Skip already sent documents"
        }
      },
      "customFields": {
        "cardTitle": "Custom fields",
        "changeLabel": "Change: {name}"
      },
      "tags": {
        "cardTitle": "Tags",
        "changeLabel": "Change: Tags",
        "placeholder": "Enter tags..."
      }
    },
    "applyChanges": "Apply changes"
  }
}
