{
  "sw-settings-attribute": {
    "general": {
      "description": "Custom fields",
      "mainMenuItemGeneral": "Custom fields",
      "placeholderSearchBar": "Search in all custom fields",
      "tooltipTechnicalName": "The technical name has to be unique and can´t be changed later"
    },
    "set": {
      "list": {
        "textHeadline": "Custom fields",
        "titleModalDelete": "Delete set",
        "textDeleteConfirm": "Do you really want to delete the set \"{name}\" ?",
        "buttonCancel": "Cancel",
        "buttonAdd": "New set",
        "columnName": "Label",
        "contextMenuEdit": "Edit",
        "buttonDelete": "Delete",
        "titleDeleteSuccess": "Success",
        "messageDeleteSuccess": "The set \"{name}\" has been deleted successfully.",
        "messageEmpty": "There are no custom fields yet."
      },
      "detail": {
        "labelTechnicalName": "Technical name",
        "textHeadline": "Custom fields-Set",
        "buttonCancel": "Cancel",
        "buttonSave": "Save",
        "titleCardInformation": "Set information",
        "labelName": "Set name",
        "placeholderName": "Type a name...",
        "labelCheckboxTranslated": "Maintain in all administration languages",
        "titleSaveSuccess": "Attribute-Set",
        "messageSaveSuccess": "The set \"{name}\" has been saved successfully.",
        "messageAttributesEmpty": "No attributes yet.",
        "addAttribute": "New custom fields",
        "buttonApply": "Save",
        "labelEntities": "Use for:",
        "placeholderEntities": "Add a usage...",
        "titleNameNotUnique": "Error",
        "messageNameNotUnique": "The technical name already exists."
      }
    },
    "attribute": {
      "detail":{
        "titleNewAttribute": "New custom fields",
        "titleEditAttribute": "Edit custom fields",
        "buttonSaveApply": "Add",
        "buttonEditApply": "Apply changes",
        "buttonCancel": "Cancel",
        "labelAttributeType": "Type",
        "labelRequired": "Required",
        "labelTechnicalName": "Technical name",
        "labelLabel": "Label",
        "buttonAddOption": "+add option",
        "labelDeleteOption": "delete",
        "labelOption": "Option {count}:",
        "labelPlaceholder": "Placeholder",
        "labelMax": "Max",
        "labelMin": "Min",
        "labelStep": "Steps",
        "labelFloat": "Float",
        "labelInt": "Integer",
        "labelNumberType": "Number type",
        "labelDatetime": "Date/Time",
        "labelDate": "Date",
        "labelTime": "Time",
        "labelDateType": "Type",
        "labelHelpText": "Help text",
        "labelTooltipText": "Tooltip text",
        "labelTimeForm": "24-Hour time format",
        "labelYes": "Yes",
        "labelNo": "No",
        "labelAttributePosition": "Position",
        "labelMultiSelect": "Multi select",
        "tooltipAttributePosition": "Controls the position of the attribute on detail pages.",
        "tooltipRequired": "Makes this custom fields required on detail pages."
      },
      "list": {
        "labelAttributeLabel": "Label",
        "labelAttributeType": "Type",
        "labelAttributePosition": "Position",
        "contextMenuAttributeResetDelete": "Restore",
        "contextMenuAttributeView": "Edit",
        "contextMenuAttributeDelete": "Delete"
      }
    },
    "types": {
      "select": "Select",
      "text": "Text field",
      "number": "Number",
      "media": "Media",
      "date": "Date / Time",
      "checkbox": "Checkbox",
      "switch": "Active/Inactive switch",
      "textEditor": "Text editor",
      "string": "Text",
      "int": "Number",
      "colorpicker": "Color picker"
    }
  }
}
